[
  {
    "id": "cpp",
    "name": "C++",
    "imgUrl": "tech/cpp.png",
    "description": "Eine alte Sprache die sich in die modernen einreiht"
  },
  {
    "id": "java",
    "name": "Java",
    "imgUrl": "tech/java.png",
    "description": "Sprache mit einer mächtigen Plattform"
  },
  {
    "id": "js",
    "imgUrl": "tech/js.png",
    "name": "JavaScript",
    "description": "Sprache des Internets und noch viel mehr"
  },
  {
    "id": "python",
    "name": "Python",
    "imgUrl": "tech/py.png",
    "description": "Starke Skriptsprache alle Zwecke"
  }
]
